data_processing_m1/__init__.py
data_processing_m1/crf_data.py
data_processing_m1/location_data.py
data_processing_m1/sensor_data.py
data_processing_m2/__init__.py
data_processing_m2/crf_data.py
data_processing_m2/location_data.py
data_processing_m2/sensor_data.py
model1/__init__.py
model1/dataloader.py
model1/model.py
model1/predictor.py
model2/__init__.py
model2/dataloader.py
model2/model.py
model2/predictor.py
ga_safer-0.2.4.dist-info/METADATA
ga_safer-0.2.4.dist-info/WHEEL
ga_safer-0.2.4.dist-info/top_level.txt
ga_safer-0.2.4.dist-info/RECORD
